setup.py
corecluster/__init__.py
corecluster/app.py
corecluster/settings.py
corecluster/settings_cluster_interface.py
corecluster/urls.py
corecluster/urls_cluster_interface.py
corecluster/version.py
corecluster/wsgi.py
corecluster/wsgi_cluster_interface.py
corecluster.egg-info/PKG-INFO
corecluster.egg-info/SOURCES.txt
corecluster.egg-info/dependency_links.txt
corecluster.egg-info/requires.txt
corecluster.egg-info/top_level.txt
corecluster/agents/__init__.py
corecluster/agents/base_agent.py
corecluster/agents/console.py
corecluster/agents/network.py
corecluster/agents/vm.py
corecluster/cache/__init__.py
corecluster/cache/data_chunk.py
corecluster/cache/model.py
corecluster/cache/task.py
corecluster/cache/drivers/__init__.py
corecluster/cache/drivers/cache_interface.py
corecluster/cache/drivers/redis_driver.py
corecluster/exceptions/__init__.py
corecluster/exceptions/agent.py
corecluster/hooks/__init__.py
corecluster/hooks/node_libvirt.py
corecluster/hooks/vm.py
corecluster/hooks/vm_cleanup_db.py
corecluster/hooks/vm_cleanup_image_libvirt.py
corecluster/hooks/vm_cleanup_task.py
corecluster/migrations/0001_initial.py
corecluster/migrations/0020_help_text.py
corecluster/migrations/0021_task_modification_time.py
corecluster/migrations/0022_template_hdd.py
corecluster/migrations/0023_reorder_hardware.py
corecluster/migrations/0024_agents.py
corecluster/migrations/0025_task_ordering.py
corecluster/migrations/0026_null_on_delete.py
corecluster/migrations/0027_task_owners.py
corecluster/migrations/0028_task_version.py
corecluster/migrations/0029_task_version.py
corecluster/migrations/0030_task_repeat.py
corecluster/migrations/0031_related_tasks.py
corecluster/migrations/0032_redirected_set.py
corecluster/migrations/0033_api_stats.py
corecluster/migrations/0034_rename_networking.py
corecluster/migrations/0035_rename_foreign_keys.py
corecluster/migrations/0036_subnet_v_id.py
corecluster/migrations/0037_network_quota.py
corecluster/migrations/0038_delete_task_table.py
corecluster/migrations/0039_agent_authorized_keys.py
corecluster/migrations/0040_timedelta.py
corecluster/migrations/0041_vm_vnc_address.py
corecluster/migrations/0042_ipv6.py
