Metadata-Version: 1.1
Name: corecluster
Version: 17.4.1
Summary: CloudOver core IaaS system
Home-page: http://cloudover.org/corecluster/
Author: Marta Nabozny
Author-email: martastrzet@gmail.com
License: UNKNOWN
Download-URL: https://github.com/cloudOver/CoreCluster/archive/master.zip
Keywords: corecluster,cloudover,cloud
Platform: UNKNOWN
